geo_coor/__init__.py
geo_coor/cli.py
geo_coor/config.py
geo_coor/core.py
geo_coor/api/__init__.py
geo_coor/api/utils.py
geo_coor/test/__init__.py
geo_coor/test/test.py
geo_coor/test/asset/csv/WGS84_TWD97.csv
geo_coor-0.0.0.dist-info/LICENSE
geo_coor-0.0.0.dist-info/METADATA
geo_coor-0.0.0.dist-info/WHEEL
geo_coor-0.0.0.dist-info/entry_points.txt
geo_coor-0.0.0.dist-info/top_level.txt
geo_coor-0.0.0.dist-info/zip-safe
geo_coor-0.0.0.dist-info/RECORD
