Metadata-Version: 2.1
Name: geo-coor
Version: 0.0.0
Summary: Longitude and latitude coordinate conversion ( TWD97 <--> WGS84) 經緯度座標轉換 (TWD97互轉WGS84)
Home-page: https://github.com/CarsonSlovoka/geo-coor/tree/master
Author: Carson
Author-email: jackparadise520a@gmail.com
License: BSD 3-Clause
Project-URL: Homepage, https://github.com/CarsonSlovoka/geo-coor/tree/master
Project-URL: Documentation, https://carsonslovoka.github.io/geo-coor/en/index.html
Project-URL: Code, https://github.com/CarsonSlovoka/geo-coor/tree/master
Project-URL: Issue Tracker, https://github.com/CarsonSlovoka/geo-coor/issues
Project-URL: Download, https://github.com/CarsonSlovoka/geo-coor/tree/master
Keywords: opencv
Platform: UNKNOWN
Classifier: Development Status :: 3 - Alpha
Classifier: License :: OSI Approved :: BSD License
Classifier: Natural Language :: Chinese (Traditional)
Classifier: Natural Language :: English
Classifier: Operating System :: Microsoft
Classifier: Operating System :: POSIX
Classifier: Operating System :: Unix
Classifier: Operating System :: MacOS
Classifier: Programming Language :: Python :: 3 :: Only
Classifier: Programming Language :: Python :: 3.6
Classifier: Programming Language :: Python :: 3.7
Classifier: Programming Language :: Python :: 3.8
Classifier: Programming Language :: Python :: 3.9
Classifier: Topic :: Scientific/Engineering :: Information Analysis
Requires-Python: >=3.6.2,
Requires-Dist: pandas
Requires-Dist: numpy
Requires-Dist: openpyxl
